[{"src":"portfolio-images/09 Nest 2021 SODIC STRIP/024-85788999-6269-427c-80e3-4c78b06c4288.jpg","dest":"scraps/pf/nest/09.jpg"},{"src":"portfolio-images/10 B 1-12 Residential Appartment 2018 West Town Sodic/001-0106b936-9a92-4d70-a0e8-bc35f2425b2f.jpg","dest":"scraps/pf/b112/01.jpg"},{"src":"portfolio-images/10 B 1-12 Residential Appartment 2018 West Town Sodic/004-05185105-4214-4291-8154-567a02c2382b.jpg","dest":"scraps/pf/b112/02.jpg"},{"src":"portfolio-images/10 B 1-12 Residential Appartment 2018 West Town Sodic/006-155fb397-5904-49b3-9517-739fc492ee6d.jpg","dest":"scraps/pf/b112/03.jpg"},{"src":"portfolio-images/10 B 1-12 Residential Appartment 2018 West Town Sodic/007-1d40af96-1275-4c1d-b342-e4dfb19f418e.jpg","dest":"scraps/pf/b112/04.jpg"},{"src":"portfolio-images/10 B 1-12 Residential Appartment 2018 West Town Sodic/014-4578528f-8300-4977-af62-719903997c66.jpg","dest":"scraps/pf/b112/05.jpg"},{"src":"portfolio-images/10 B 1-12 Residential Appartment 2018 West Town Sodic/020-7de32944-29d6-4184-aae3-d7240d41b3b0.jpg","dest":"scraps/pf/b112/06.jpg"},{"src":"portfolio-images/10 B 1-12 Residential Appartment 2018 West Town Sodic/023-86ad9581-c342-4135-859a-2f7a637e73f8.jpg","dest":"scraps/pf/b112/07.jpg"},{"src":"portfolio-images/10 B 1-12 Residential Appartment 2018 West Town Sodic/024-673b53da631d5965.jpg","dest":"scraps/pf/b112/08.jpg"},{"src":"portfolio-images/10 B 1-12 Residential Appartment 2018 West Town Sodic/030-ca643a6d-10e8-4fc6-97d4-4b29d08dfd13.jpg","dest":"scraps/pf/b112/09.jpg"},{"src":"portfolio-images/11 SD-1 Penthouse 2019 El Patio/003-12b5a242-f508-4100-a1d9-03065e0a708f.jpg","dest":"scraps/pf/sd1/01.jpg"},{"src":"portfolio-images/11 SD-1 Penthouse 2019 El Patio/005-1aa4eee0-9b52-4e92-861a-14878586918e.jpg","dest":"scraps/pf/sd1/02.jpg"},{"src":"portfolio-images/11 SD-1 Penthouse 2019 El Patio/010-3c4fb245-f770-47ee-b04a-3536a82a5708.jpg","dest":"scraps/pf/sd1/03.jpg"},{"src":"portfolio-images/11 SD-1 Penthouse 2019 El Patio/012-53a1c5da-7efa-4ee5-bdb0-a85f2270958c.jpg","dest":"scraps/pf/sd1/04.jpg"},{"src":"portfolio-images/11 SD-1 Penthouse 2019 El Patio/014-5b2432db-26b2-4cde-bc4c-fec7373133a4.jpg","dest":"scraps/pf/sd1/05.jpg"},{"src":"portfolio-images/11 SD-1 Penthouse 2019 El Patio/015-5d4220db-eabb-4a0c-be90-245ad8e5625c.jpg","dest":"scraps/pf/sd1/06.jpg"},{"src":"portfolio-images/11 SD-1 Penthouse 2019 El Patio/016-6ebf9ac6-f073-47cc-a6b2-f321f61901c7.jpg","dest":"scraps/pf/sd1/07.jpg"},{"src":"portfolio-images/11 SD-1 Penthouse 2019 El Patio/017-b71de623f8694529.jpg","dest":"scraps/pf/sd1/08.jpg"},{"src":"portfolio-images/11 SD-1 Penthouse 2019 El Patio/022-9cf1def3-993c-41c4-9972-d4afc41cdb98.jpg","dest":"scraps/pf/sd1/09.jpg"}]